uci/__init__.py
uci/stop_words.py
uci-1.0.6.dist-info/LICENSE
uci-1.0.6.dist-info/METADATA
uci-1.0.6.dist-info/WHEEL
uci-1.0.6.dist-info/top_level.txt
uci-1.0.6.dist-info/RECORD
